cnl_launcher/__init__.py
cnl_launcher/launcher.py
cnl_launcher/launcher_local.py
cnl_launcher-0.0.1.data/scripts/cnl_launcher
cnl_launcher-0.0.1.data/scripts/local_launcher
cnl_launcher-0.0.1.dist-info/LICENSE
cnl_launcher-0.0.1.dist-info/METADATA
cnl_launcher-0.0.1.dist-info/WHEEL
cnl_launcher-0.0.1.dist-info/top_level.txt
cnl_launcher-0.0.1.dist-info/RECORD
