Metadata-Version: 2.1
Name: cnl-launcher
Version: 0.0.1
Summary: New launcher for TACC
Home-page: UNKNOWN
Author: CNL lab
License: UNKNOWN
Platform: UNKNOWN
Classifier: Programming Language :: Python :: 3
Classifier: License :: OSI Approved :: MIT License
Classifier: Operating System :: OS Independent
